coopr.gdp-1.2-py2.7-nspkg.pth
coopr/gdp/__init__.py
coopr/gdp/bigm.py
coopr/gdp/chull.py
coopr/gdp/disjunct.py
coopr/gdp/plugins/__init__.py
coopr/gdp/plugins/bigm.py
coopr/gdp/plugins/bilinear.py
coopr/gdp/plugins/chull.py
coopr/gdp/tests/__init__.py
coopr/gdp/tests/test_gdp.py
coopr.gdp-1.2.dist-info/DESCRIPTION.rst
coopr.gdp-1.2.dist-info/METADATA
coopr.gdp-1.2.dist-info/metadata.json
coopr.gdp-1.2.dist-info/namespace_packages.txt
coopr.gdp-1.2.dist-info/RECORD
coopr.gdp-1.2.dist-info/top_level.txt
coopr.gdp-1.2.dist-info/WHEEL
