Metadata-Version: 2.0
Name: coopr.gdp
Version: 1.2
Summary: Generalized Disjunctive Programming (GDP) extensions to the Pyomo environment
Home-page: https://software.sandia.gov/svn/public/coopr/coopr.gdp
Author: John Siirola
Author-email: jdsiiro@sandia.gov
License: BSD
Keywords: optimization
Platform: any
Classifier: Development Status :: 4 - Beta
Classifier: Intended Audience :: End Users/Desktop
Classifier: Intended Audience :: Science/Research
Classifier: License :: OSI Approved :: BSD License
Classifier: Natural Language :: English
Classifier: Operating System :: Microsoft :: Windows
Classifier: Operating System :: Unix
Classifier: Programming Language :: Python
Classifier: Programming Language :: Unix Shell
Classifier: Topic :: Scientific/Engineering :: Mathematics
Classifier: Topic :: Software Development :: Libraries :: Python Modules
Classifier: Topic :: Scientific/Engineering
